cryptotrading_agent/__init__.py
cryptotrading_agent/agent.py
cryptotrading_agent/cli.py
cryptotrading_agent/core.py
cryptotrading_agent/exceptions.py
cryptotrading_agent/structured_local.py
cryptotrading_agent/technical_analyzer.py
cryptotrading_agent/renderers/__init__.py
cryptotrading_agent/renderers/rich_structured.py
autodegen-0.2.5.dist-info/METADATA
autodegen-0.2.5.dist-info/WHEEL
autodegen-0.2.5.dist-info/entry_points.txt
autodegen-0.2.5.dist-info/licenses/LICENSE
autodegen-0.2.5.dist-info/RECORD
