Metadata-Version: 2.4
Name: autodegen
Version: 0.2.5
Summary: Production-ready crypto trading analysis agent with LLM hardening
Project-URL: Homepage, https://github.com/taygundogan/cryptotrading-agent
Project-URL: Repository, https://github.com/taygundogan/cryptotrading-agent
Project-URL: Issues, https://github.com/taygundogan/cryptotrading-agent/issues
Project-URL: Documentation, https://github.com/taygundogan/cryptotrading-agent#readme
Author-email: Taygun Dogan <taygundogan@example.com>
License: MIT
License-File: LICENSE
Keywords: agent,analysis,binance,crypto,defi,llm,trading
Classifier: Development Status :: 4 - Beta
Classifier: Intended Audience :: Financial and Insurance Industry
Classifier: License :: OSI Approved :: MIT License
Classifier: Operating System :: OS Independent
Classifier: Programming Language :: Python :: 3
Classifier: Programming Language :: Python :: 3.9
Classifier: Programming Language :: Python :: 3.10
Classifier: Programming Language :: Python :: 3.11
Classifier: Programming Language :: Python :: 3.12
Classifier: Topic :: Office/Business :: Financial :: Investment
Classifier: Topic :: Scientific/Engineering :: Artificial Intelligence
Requires-Python: >=3.9
Requires-Dist: aiohttp>=3.9.0
Requires-Dist: aiosqlite>=0.19.0
Requires-Dist: anthropic>=0.7.0
Requires-Dist: colorama>=0.4.6
Requires-Dist: fastapi>=0.100.0
Requires-Dist: httpx>=0.27.0
Requires-Dist: numpy>=1.26.0
Requires-Dist: openai>=1.0.0
Requires-Dist: pandas>=2.2.0
Requires-Dist: pydantic>=2.7.0
Requires-Dist: python-binance>=1.0.19
Requires-Dist: python-dotenv>=1.0.0
Requires-Dist: rich>=13.7.0
Requires-Dist: scipy>=1.11.0
Requires-Dist: ta-lib>=0.4.28
Requires-Dist: typer>=0.12.0
Requires-Dist: typing-extensions>=4.8.0
Requires-Dist: uvicorn>=0.20.0
Requires-Dist: websockets>=11.0
Provides-Extra: dev
Requires-Dist: black>=24.0.0; extra == 'dev'
Requires-Dist: pytest-asyncio>=0.25.0; extra == 'dev'
Requires-Dist: pytest-mock>=3.14.0; extra == 'dev'
Requires-Dist: pytest>=8.0.0; extra == 'dev'
Requires-Dist: ruff>=0.6.0; extra == 'dev'
Provides-Extra: test
Requires-Dist: pytest-asyncio>=0.25.0; extra == 'test'
Requires-Dist: pytest-mock>=3.14.0; extra == 'test'
Requires-Dist: pytest>=8.0.0; extra == 'test'
